[
  {
    "name": "Container",
    "open": true,
    "items": [
      {
        "label": "Background Color",
        "cssVar": "--nuraly-color-chatbot-background"
      },
      {
        "label": "Border Color",
        "cssVar": "--nuraly-color-chatbot-border"
      },
      {
        "label": "Border Radius",
        "cssVar": "--nuraly-border-radius-chatbot"
      }
    ]
  },
  {
    "name": "Messages",
    "open": false,
    "items": [
      {
        "label": "User Message Background",
        "cssVar": "--nuraly-color-chatbot-message-user-background"
      },
      {
        "label": "User Message Text",
        "cssVar": "--nuraly-color-chatbot-message-user-text"
      },
      {
        "label": "Bot Message Background",
        "cssVar": "--nuraly-color-chatbot-message-bot-background"
      },
      {
        "label": "Bot Message Text",
        "cssVar": "--nuraly-color-chatbot-message-bot-text"
      }
    ]
  },
  {
    "name": "Input",
    "open": false,
    "items": [
      {
        "label": "Input Background",
        "cssVar": "--nuraly-color-chatbot-input-background"
      },
      {
        "label": "Input Border",
        "cssVar": "--nuraly-color-chatbot-input-border"
      },
      {
        "label": "Placeholder Color",
        "cssVar": "--nuraly-color-chatbot-placeholder"
      }
    ]
  },
  {
    "name": "Accent",
    "open": false,
    "items": [
      {
        "label": "Accent Color",
        "cssVar": "--nuraly-color-chatbot-accent"
      },
      {
        "label": "Send Button Color",
        "cssVar": "--nuraly-color-chatbot-send-button"
      }
    ]
  }
]
